virenamer/__init__.py
virenamer/cli.py
virenamer-1.1.0.dist-info/entry_points.txt
virenamer-1.1.0.dist-info/LICENSE
virenamer-1.1.0.dist-info/WHEEL
virenamer-1.1.0.dist-info/METADATA
virenamer-1.1.0.dist-info/RECORD
