Metadata-Version: 2.1
Name: virenamer
Version: 1.1.0
Summary: Rename files by editing their paths directly in Vi (or in any other editor)
License: Apache-2.0
Author: Sébastien MB
Author-email: seb@essembeh.org
Requires-Python: >=3.8,<4.0
Classifier: Development Status :: 4 - Beta
Classifier: License :: OSI Approved :: Apache Software License
Classifier: Programming Language :: Python :: 3
Classifier: Programming Language :: Python :: 3.10
Classifier: Programming Language :: Python :: 3.8
Classifier: Programming Language :: Python :: 3.9
Classifier: Topic :: Utilities
Requires-Dist: colorama
